{"nodes": [{"id": "Kenshi Yonezu", "group": 0, "level": 0, "size": 28}, {"id": "OFFICIAL HIGE DANDISM", "group": 1, "level": 1, "size": 22}, {"id": "King Gnu", "group": 1, "level": 1, "size": 22}, {"id": "Vaundy", "group": 1, "level": 1, "size": 22}, {"id": "Yorushika", "group": 1, "level": 1, "size": 22}, {"id": "yama", "group": 1, "level": 1, "size": 22}, {"id": "Eve", "group": 2, "level": 2, "size": 16}, {"id": "Tatsuya Kitani", "group": 2, "level": 2, "size": 16}, {"id": "Yuuri", "group": 2, "level": 2, "size": 16}, {"id": "Mrs. Green Apple", "group": 2, "level": 2, "size": 16}, {"id": "Ryokuoushoku Shakai", "group": 2, "level": 2, "size": 16}, {"id": "Rokudenashi", "group": 2, "level": 2, "size": 16}, {"id": "YOASOBI", "group": 2, "level": 2, "size": 16}, {"id": "milet", "group": 3, "level": 3, "size": 12}, {"id": "Creepy Nuts", "group": 3, "level": 3, "size": 12}, {"id": "ALI", "group": 3, "level": 3, "size": 12}, {"id": "MAISONdes", "group": 3, "level": 3, "size": 12}, {"id": "Back Number", "group": 3, "level": 3, "size": 12}, {"id": "aimyon", "group": 3, "level": 3, "size": 12}, {"id": "Novelbright", "group": 3, "level": 3, "size": 12}, {"id": "Lilas Ikuta", "group": 3, "level": 3, "size": 12}], "links": [{"source": "Kenshi Yonezu", "target": "OFFICIAL HIGE DANDISM"}, {"source": "Kenshi Yonezu", "target": "King Gnu"}, {"source": "Kenshi Yonezu", "target": "Vaundy"}, {"source": "Kenshi Yonezu", "target": "Yorushika"}, {"source": "Kenshi Yonezu", "target": "yama"}, {"source": "yama", "target": "Eve"}, {"source": "yama", "target": "Tatsuya Kitani"}, {"source": "yama", "target": "King Gnu"}, {"source": "yama", "target": "Yorushika"}, {"source": "yama", "target": "Vaundy"}, {"source": "OFFICIAL HIGE DANDISM", "target": "Yuuri"}, {"source": "OFFICIAL HIGE DANDISM", "target": "Kenshi Yonezu"}, {"source": "OFFICIAL HIGE DANDISM", "target": "Vaundy"}, {"source": "OFFICIAL HIGE DANDISM", "target": "King Gnu"}, {"source": "OFFICIAL HIGE DANDISM", "target": "Mrs. Green Apple"}, {"source": "King Gnu", "target": "Vaundy"}, {"source": "King Gnu", "target": "Kenshi Yonezu"}, {"source": "King Gnu", "target": "Yorushika"}, {"source": "King Gnu", "target": "OFFICIAL HIGE DANDISM"}, {"source": "King Gnu", "target": "Yuuri"}, {"source": "Vaundy", "target": "OFFICIAL HIGE DANDISM"}, {"source": "Vaundy", "target": "Kenshi Yonezu"}, {"source": "Vaundy", "target": "King Gnu"}, {"source": "Vaundy", "target": "Ryokuoushoku Shakai"}, {"source": "Vaundy", "target": "Yuuri"}, {"source": "Yorushika", "target": "Kenshi Yonezu"}, {"source": "Yorushika", "target": "OFFICIAL HIGE DANDISM"}, {"source": "Yorushika", "target": "Rokudenashi"}, {"source": "Yorushika", "target": "YOASOBI"}, {"source": "Yorushika", "target": "yama"}, {"source": "Eve", "target": "yama"}, {"source": "Eve", "target": "YOASOBI"}, {"source": "Eve", "target": "Kenshi Yonezu"}, {"source": "Eve", "target": "Tatsuya Kitani"}, {"source": "Eve", "target": "Yorushika"}, {"source": "Mrs. Green Apple", "target": "OFFICIAL HIGE DANDISM"}, {"source": "Mrs. Green Apple", "target": "Kenshi Yonezu"}, {"source": "Mrs. Green Apple", "target": "Vaundy"}, {"source": "Mrs. Green Apple", "target": "Ryokuoushoku Shakai"}, {"source": "Mrs. Green Apple", "target": "Yuuri"}, {"source": "Ryokuoushoku Shakai", "target": "milet"}, {"source": "Ryokuoushoku Shakai", "target": "Kenshi Yonezu"}, {"source": "Ryokuoushoku Shakai", "target": "Creepy Nuts"}, {"source": "Ryokuoushoku Shakai", "target": "Yorushika"}, {"source": "Ryokuoushoku Shakai", "target": "King Gnu"}, {"source": "Tatsuya Kitani", "target": "Eve"}, {"source": "Tatsuya Kitani", "target": "ALI"}, {"source": "Tatsuya Kitani", "target": "Creepy Nuts"}, {"source": "Tatsuya Kitani", "target": "yama"}, {"source": "Tatsuya Kitani", "target": "MAISONdes"}, {"source": "YOASOBI", "target": "Eve"}, {"source": "YOASOBI", "target": "yama"}, {"source": "YOASOBI", "target": "Kenshi Yonezu"}, {"source": "YOASOBI", "target": "Creepy Nuts"}, {"source": "YOASOBI", "target": "Yorushika"}, {"source": "Yuuri", "target": "Back Number"}, {"source": "Yuuri", "target": "aimyon"}, {"source": "Yuuri", "target": "Kenshi Yonezu"}, {"source": "Yuuri", "target": "OFFICIAL HIGE DANDISM"}, {"source": "Yuuri", "target": "Novelbright"}, {"source": "Rokudenashi", "target": "Lilas Ikuta"}, {"source": "Rokudenashi", "target": "Yorushika"}, {"source": "Rokudenashi", "target": "Kenshi Yonezu"}, {"source": "Rokudenashi", "target": "YOASOBI"}, {"source": "Rokudenashi", "target": "yama"}]}